{"v":3,"stories":{"marbella-contracteditor--primary":{"id":"marbella-contracteditor--primary","name":"Primary","title":"Marbella/ContractEditor","importPath":"./src/stories/contract-editor.stories.tsx","tags":["story"],"kind":"Marbella/ContractEditor","story":"Primary","parameters":{"__id":"marbella-contracteditor--primary","docsOnly":false,"fileName":"./src/stories/contract-editor.stories.tsx"}},"marbella-contractlist--primary":{"id":"marbella-contractlist--primary","name":"Primary","title":"Marbella/ContractList","importPath":"./src/stories/contract-list.stories.tsx","tags":["story"],"kind":"Marbella/ContractList","story":"Primary","parameters":{"__id":"marbella-contractlist--primary","docsOnly":false,"fileName":"./src/stories/contract-list.stories.tsx"}},"marbella-templateeditor--primary":{"id":"marbella-templateeditor--primary","name":"Primary","title":"Marbella/TemplateEditor","importPath":"./src/stories/template-editor.stories.tsx","tags":["story"],"kind":"Marbella/TemplateEditor","story":"Primary","parameters":{"__id":"marbella-templateeditor--primary","docsOnly":false,"fileName":"./src/stories/template-editor.stories.tsx"}},"marbella-templatelist--primary":{"id":"marbella-templatelist--primary","name":"Primary","title":"Marbella/TemplateList","importPath":"./src/stories/template-list.stories.tsx","tags":["story"],"kind":"Marbella/TemplateList","story":"Primary","parameters":{"__id":"marbella-templatelist--primary","docsOnly":false,"fileName":"./src/stories/template-list.stories.tsx"}}}}
